pyusher/__init__.py
pyusher/base_agent.py
pyusher/load_agent.py
pyusher/server/__init__.py
pyusher/server/connection.py
pyusher/server/eventtypes.py
pyusher/server/exceptions.py
pyusher/server/helpers.py
pyusher/server/http.py
pyusher/server/old_http.py
pyusher/server/runner.py
pyusher/server/worker.py
pyusher-0.1.2.dist-info/METADATA
pyusher-0.1.2.dist-info/WHEEL
pyusher-0.1.2.dist-info/top_level.txt
pyusher-0.1.2.dist-info/RECORD
