Metadata-Version: 2.4
Name: pyusher
Version: 0.1.2
Requires-Dist: fastapi
Requires-Dist: structlog
Requires-Dist: uvicorn
Dynamic: requires-dist
